asphalt/exceptions/__init__.py
asphalt/exceptions/api.py
asphalt/exceptions/component.py
asphalt/exceptions/py.typed
asphalt/exceptions/reporters/raygun.py
asphalt/exceptions/reporters/sentry.py
asphalt_exceptions-2.2.0.dist-info/LICENSE
asphalt_exceptions-2.2.0.dist-info/METADATA
asphalt_exceptions-2.2.0.dist-info/WHEEL
asphalt_exceptions-2.2.0.dist-info/entry_points.txt
asphalt_exceptions-2.2.0.dist-info/top_level.txt
asphalt_exceptions-2.2.0.dist-info/RECORD
