Metadata-Version: 2.1
Name: asphalt-exceptions
Version: 2.2.0
Summary: Exception reporter component for the Asphalt framework
Author-email: Alex Grönholm <alex.gronholm@nextday.fi>
License: Apache License 2.0
Project-URL: Homepage, https://github.com/asphalt-framework/asphalt-exceptions
Classifier: Development Status :: 5 - Production/Stable
Classifier: Intended Audience :: Developers
Classifier: License :: OSI Approved :: Apache Software License
Classifier: Topic :: Software Development :: Libraries :: Application Frameworks
Classifier: Typing :: Typed
Classifier: Programming Language :: Python
Classifier: Programming Language :: Python :: 3 :: Only
Classifier: Programming Language :: Python :: 3.7
Classifier: Programming Language :: Python :: 3.8
Classifier: Programming Language :: Python :: 3.9
Classifier: Programming Language :: Python :: 3.10
Classifier: Programming Language :: Python :: 3.11
Classifier: Programming Language :: Python :: 3.12
Requires-Python: >=3.7
License-File: LICENSE
Requires-Dist: asphalt ~=4.6
Requires-Dist: typing-extensions >=4.6.0 ; python_version < "3.10"
Provides-Extra: doc
Requires-Dist: asphalt-exceptions[raygun,sentry] ; extra == 'doc'
Requires-Dist: Sphinx >=7 ; extra == 'doc'
Requires-Dist: sphinx-rtd-theme >=1.3.0 ; extra == 'doc'
Requires-Dist: sphinx-autodoc-typehints >=1.2.0 ; extra == 'doc'
Provides-Extra: raygun
Requires-Dist: raygun4py >=4.3 ; extra == 'raygun'
Provides-Extra: sentry
Requires-Dist: sentry-sdk >=1.5 ; extra == 'sentry'
Provides-Extra: test
Requires-Dist: asphalt-exceptions[raygun,sentry] ; extra == 'test'
Requires-Dist: pytest ; extra == 'test'
Requires-Dist: pytest-asyncio ; extra == 'test'
Requires-Dist: pytest-cov ; extra == 'test'
Requires-Dist: pytest-mock ; extra == 'test'
